tensor_observer/__init__.py
tensor_observer/api.py
tensor_observer-0.0.4.dist-info/LICENSE
tensor_observer-0.0.4.dist-info/METADATA
tensor_observer-0.0.4.dist-info/WHEEL
tensor_observer-0.0.4.dist-info/top_level.txt
tensor_observer-0.0.4.dist-info/RECORD
