Metadata-Version: 2.1
Name: tensor-observer
Version: 0.0.4
Summary: A little api library for a TensorObserver server
Home-page: https://github.com/jannessm/tensor-observer
Author: Jannes Magnusson
Author-email: j-magnusson@t-online.de
License: GNU GPL
Keywords: tensorObserver tensorflow tensorboard pytorch
Platform: UNKNOWN
